{
    "key": "group_60c3d8bb9071b",
    "title": "Section - Facts",
    "fields": [
        {
            "key": "field_60c3d8d88cbc7",
            "label": "Facts",
            "name": "facts",
            "type": "repeater",
            "instructions": "Add facts that will display in a slider format.",
            "required": 0,
            "conditional_logic": 0,
            "wrapper": {
                "width": "",
                "class": "",
                "id": ""
            },
            "collapsed": "",
            "min": 0,
            "max": 0,
            "layout": "block",
            "button_label": "",
            "sub_fields": [
                {
                    "key": "field_60c3d9098cbc8",
                    "label": "Title 1",
                    "name": "title_1",
                    "type": "text",
                    "instructions": "",
                    "required": 1,
                    "conditional_logic": 0,
                    "wrapper": {
                        "width": "50",
                        "class": "",
                        "id": ""
                    },
                    "default_value": "",
                    "placeholder": "",
                    "prepend": "",
                    "append": "",
                    "maxlength": ""
                },
                {
                    "key": "field_60c3d9178cbc9",
                    "label": "Title 2",
                    "name": "title_2",
                    "type": "text",
                    "instructions": "",
                    "required": 1,
                    "conditional_logic": 0,
                    "wrapper": {
                        "width": "50",
                        "class": "",
                        "id": ""
                    },
                    "default_value": "",
                    "placeholder": "",
                    "prepend": "",
                    "append": "",
                    "maxlength": ""
                },
                {
                    "key": "field_60c3d91e8cbca",
                    "label": "Text",
                    "name": "text",
                    "type": "wysiwyg",
                    "instructions": "",
                    "required": 1,
                    "conditional_logic": 0,
                    "wrapper": {
                        "width": "",
                        "class": "",
                        "id": ""
                    },
                    "default_value": "",
                    "tabs": "all",
                    "toolbar": "basic",
                    "media_upload": 0,
                    "delay": 0
                },
                {
                    "key": "field_60c4a930bd00b",
                    "label": "Button",
                    "name": "button",
                    "type": "link",
                    "instructions": "",
                    "required": 0,
                    "conditional_logic": 0,
                    "wrapper": {
                        "width": "",
                        "class": "",
                        "id": ""
                    },
                    "return_format": "array"
                },
                {
                    "key": "field_60c3d92e8cbcb",
                    "label": "Icon",
                    "name": "icon",
                    "type": "image",
                    "instructions": "",
                    "required": 1,
                    "conditional_logic": 0,
                    "wrapper": {
                        "width": "50",
                        "class": "",
                        "id": ""
                    },
                    "return_format": "id",
                    "preview_size": "medium",
                    "library": "all",
                    "min_width": "",
                    "min_height": "",
                    "min_size": "",
                    "max_width": "",
                    "max_height": "",
                    "max_size": "",
                    "mime_types": ""
                },
                {
                    "key": "field_60c3d9408cbcc",
                    "label": "Featured Image",
                    "name": "featured_image",
                    "type": "group",
                    "instructions": "",
                    "required": 1,
                    "conditional_logic": 0,
                    "wrapper": {
                        "width": "50",
                        "class": "",
                        "id": ""
                    },
                    "layout": "block",
                    "sub_fields": [
                        {
                            "key": "field_60f972f55fc77",
                            "label": "Media Type",
                            "name": "media_type",
                            "type": "button_group",
                            "instructions": "",
                            "required": 0,
                            "conditional_logic": 0,
                            "wrapper": {
                                "width": "",
                                "class": "",
                                "id": ""
                            },
                            "choices": {
                                "image": "Image",
                                "video": "Video"
                            },
                            "allow_null": 0,
                            "default_value": "",
                            "layout": "horizontal",
                            "return_format": "value"
                        },
                        {
                            "key": "field_60f973065fc78",
                            "label": "Image",
                            "name": "image",
                            "type": "image",
                            "instructions": "",
                            "required": 0,
                            "conditional_logic": 0,
                            "wrapper": {
                                "width": "",
                                "class": "",
                                "id": ""
                            },
                            "return_format": "id",
                            "preview_size": "medium",
                            "library": "all",
                            "min_width": "",
                            "min_height": "",
                            "min_size": "",
                            "max_width": "",
                            "max_height": "",
                            "max_size": "",
                            "mime_types": ""
                        },
                        {
                            "key": "field_60f973105fc79",
                            "label": "Video",
                            "name": "video",
                            "type": "file",
                            "instructions": "",
                            "required": 0,
                            "conditional_logic": [
                                [
                                    {
                                        "field": "field_60f972f55fc77",
                                        "operator": "==",
                                        "value": "video"
                                    }
                                ]
                            ],
                            "wrapper": {
                                "width": "",
                                "class": "",
                                "id": ""
                            },
                            "return_format": "id",
                            "library": "all",
                            "min_size": "",
                            "max_size": "",
                            "mime_types": "mp4,webm"
                        }
                    ]
                }
            ]
        },
        {
            "key": "field_60d5a5a0fb68d",
            "label": "Spacing",
            "name": "spacing",
            "type": "clone",
            "instructions": "",
            "required": 0,
            "conditional_logic": 0,
            "wrapper": {
                "width": "",
                "class": "",
                "id": ""
            },
            "clone": [
                "group_60cc939725475"
            ],
            "display": "seamless",
            "layout": "block",
            "prefix_label": 0,
            "prefix_name": 0
        }
    ],
    "location": [
        [
            {
                "param": "block",
                "operator": "==",
                "value": ""
            }
        ]
    ],
    "menu_order": 0,
    "position": "normal",
    "style": "default",
    "label_placement": "top",
    "instruction_placement": "label",
    "hide_on_screen": "",
    "active": true,
    "description": "",
    "modified": 1666949059
}